pyfroniusreg/froniusreg.py
pyfroniusreg/gen24_primo_symo_inverter_register_map_float.py
pyfroniusreg/gen24_primo_symo_inverter_register_map_float_storage.py
pyfroniusreg/gen24_primo_symo_inverter_register_map_int_sf.py
pyfroniusreg/gen24_primo_symo_inverter_register_map_int_sf_storage.py
pyfroniusreg/gen24_registers_orig.py
pyfroniusreg/smart_meter_register_map_float.py
pyfroniusreg/smart_meter_register_map_int_sf.py
pyfroniusreg/tauro_eco_inverter_register_map_float.py
pyfroniusreg/tauro_eco_inverter_register_map_int_sf.py
pyfroniusreg/tauro_inverter_register_map_float.py
pyfroniusreg/tauro_inverter_register_map_int_sf.py
pyfroniusreg/verto_inverter_register_map_3mppt_float.py
pyfroniusreg/verto_inverter_register_map_3mppt_int_sf.py
pyfroniusreg/verto_inverter_register_map_4mppt_float.py
pyfroniusreg/verto_inverter_register_map_4mppt_int_sf.py
pyfroniusreg-0.2.3.dist-info/METADATA
pyfroniusreg-0.2.3.dist-info/WHEEL
pyfroniusreg-0.2.3.dist-info/licenses/LICENSE
pyfroniusreg-0.2.3.dist-info/RECORD
