Metadata-Version: 2.4
Name: pyFroniusReg
Version: 0.2.3
Summary: A library to make interacting with Fronius inverters and storage systems simpler
Project-URL: Homepage, https://git.pwarren.id.au/pwarren/PyFroniusReg/
Project-URL: Issues, https://git.pwarren.id.au/pwarren/PyFroniusReg/issues
Author-email: Paul Warren <pwarren@pwarren.id.au>
License-File: LICENSE
Classifier: Development Status :: 3 - Alpha
Classifier: License :: OSI Approved :: GNU Affero General Public License v3 or later (AGPLv3+)
Classifier: Operating System :: OS Independent
Classifier: Programming Language :: Python :: 3
Requires-Python: >=3.9
Requires-Dist: pymodbus==3.7.*
